[
  {
    "package": "distributional",
    "url": "https://github.com/mitchelloharawild/distributional",
    "via": ["fasster", "fabletools"],
    "from": "fasster"
  },
  {
    "package": "fabletools",
    "url": "https://github.com/tidyverts/fabletools",
    "via": ["fasster"],
    "from": "fasster"
  },
  {
    "package": "ggplot2",
    "url": "https://github.com/tidyverse/ggplot2",
    "via": ["ggtime"],
    "from": "ggtime"
  },
  {
    "package": "mixtime",
    "url": "https://github.com/mitchelloharawild/mixtime",
    "via": ["ggtime"],
    "from": "ggtime"
  },
  {
    "package": "pkgmeta",
    "url": "https://github.com/robjhyndman/pkgmeta",
    "via": ["spiderorchid"],
    "from": "spiderorchid"
  },
  {
    "package": "rAltmetric",
    "url": "https://github.com/ropensci/rAltmetric",
    "via": ["rcademy"],
    "from": "rcademy"
  }
]
